pypi_test_gifconverter/__init__.py
pypi_test_gifconverter/gifconverter.py
pypi_test_gifconverter-1.0.1.dist-info/LICENSE
pypi_test_gifconverter-1.0.1.dist-info/METADATA
pypi_test_gifconverter-1.0.1.dist-info/WHEEL
pypi_test_gifconverter-1.0.1.dist-info/top_level.txt
pypi_test_gifconverter-1.0.1.dist-info/RECORD
